Minilab3/recieve.sv
//for recieving, when a transition from 1->0 is detected, this is considered
//the start bit;
//after this, 8 bits of data are recieved
//after this, remain at 1
module recieve (
    input wire clk,
    //NOTE: ONLY SAMPLE WHEN b_en IS HIGH!
    input wire b_en,
    input wire rst,
    input wire i_iocs,
    input wire i_rx,
    input wire i_iorw,
    //Receive Data Available: indicates that a byte of data has been recieved
    //and is ready to be read from the SPART to the processor. 
    output wire o_rda,
    output wire [7:0] o_data
);
  localparam IDLE = 2'b00;
  localparam START_BIT = 2'b01;
  localparam READING = 2'b10;
  localparam END_BIT = 2'b11;
  logic [1:0] curr_state, next_state;
  logic [2:0] counter;
  //NOTE: n=4, hence oversampling of 16!!!!
  logic [2:0] start_counter;
  logic [3:0] t_counter;
  reg [7:0] buffer;
  reg i_rx_reg;

  assign o_data = buffer;

  always @(posedge clk) begin
    if (!rst) i_rx_reg <= 1'b0;
    else i_rx_reg <= i_rx;
  end

  //next_state logic
  //once we detect a negedge on i_rx, wait 2 baud cycles to transition?
  always_comb begin
    //idle state
    next_state = 2'b00;
    case (curr_state)
      //if current state is IDLE and reciever samples a 0, transition to
      //START_BIT
      IDLE: begin
        if (i_rx == 1'b0 && i_rx_reg == 1'b1) next_state = START_BIT;
        else next_state = IDLE;
      end
      START_BIT: begin
        if (start_counter == 3'b111) next_state = READING;
        else next_state = START_BIT;
      end
      READING: begin
        if (counter != 3'b111) next_state = READING;
        else next_state = END_BIT;
      end
      END_BIT: begin
        if (start_counter == 3'b111) next_state = IDLE;
        else next_state = END_BIT;
      end
    endcase
  end

  //when transitioning from END_BIT to IDLE, indicates a read has been
  //completed
  //when iorw==1, indicates a read. set o_rda to 0 once this read has been
  //completed?
  reg rda;
  assign o_rda = rda;
  always @(posedge clk) begin
    if (!rst) rda <= 1'b0;
    else begin
      if (b_en) begin
        if (curr_state == END_BIT && next_state == IDLE) rda <= 1'b1;
        if (i_iocs && i_iorw == 1'b1) rda <= 1'b0;
      end
    end
  end

  always @(posedge clk) begin
    if (!rst) curr_state <= IDLE;
    else begin
      if (b_en) begin
        curr_state <= next_state;
      end
    end
  end

  //TODO: check if i_rx is maintained at 0 to check for noise?
  always @(posedge clk) begin
    if (!rst) begin
      buffer <= 8'b0;
      counter <= 3'b0;
      start_counter <= 3'b0;
      t_counter <= 0;
    end else begin
      if (b_en) begin
        case (curr_state)
          IDLE: begin
            buffer <= buffer;
            counter <= 3'b0;
            t_counter <= 0;
            start_counter <= 0;
          end
          START_BIT: begin
            buffer <= buffer;
            counter <= 3'b0;
            start_counter <= start_counter + 1;
            t_counter <= 0;
          end
          READING: begin
            start_counter <= 0;
            //check to be in the middle of the bit
            if (t_counter == 4'b1111) begin
              buffer <= {buffer[6:0], i_rx};
              counter <= counter + 1;
              t_counter <= 0;
            end else begin
              t_counter <= t_counter + 1;
            end
          end
          END_BIT: begin
            buffer <= buffer;
            start_counter <= start_counter + 1;
            t_counter <= 0;
          end
        endcase
      end
    end
  end

endmodule

Minilab3/brg.sv
//implemented using a down counter and a decoder
//enable signal is asserted for a duration of one CLK period, with a frequency
//of 2^n x baud_rate. n ranges from 2 to 4
//
//frequency of clk driving the BRG module will vary
//BRG must be programmable to maintain a fixed baud rate despite changing
//clock frequency
//
//Programming is achieved by the processor loading 2 bytes, DB(high) and
//DB(low) into the divisor buffer. 



module brg (
    input wire clk,
    input wire rst,
    input wire [1:0] i_ioaddr_brg,
    input wire [7:0] i_brg_bus,
    output wire en
);
  reg [15:0] div_buf;
  reg [15:0] down_counter;
  always @(posedge clk) begin
    if (!rst) div_buf <= 16'b0;
    else begin
      if (i_ioaddr_brg == 2'b11) begin
        div_buf[15:8] <= i_brg_bus;
        down_counter[15:8] <= i_brg_bus;
      end else if (i_ioaddr_brg == 2'b10) begin
        div_buf[7:0] <= i_brg_bus;
        down_counter[7:0] <= i_brg_bus;
      end  //if neither DB(high) or DB(low) are being set, act normally(?)
      else begin
        if (down_counter == 0) down_counter <= div_buf;
        else down_counter <= down_counter - 1;

      end
    end
  end
  assign en = (down_counter == 0);
endmodule

Minilab3/recieve_tb.sv
module recieve_tb ();
  logic clk;
  logic b_en;
  logic rst;
  logic i_iocs;
  logic i_rx;
  logic i_iorw;
  logic o_rda;
  logic [7:0] o_data;

  initial clk = 0;
  always begin
    clk = #5 ~clk;
  end
  initial rst = 1;
  initial i_rx = 1'b1;

  logic [1:0] i_ioaddr_brg;
  logic [7:0] i_brg_bus;
  brg baud_rate_gen (
      .clk(clk),
      .rst(rst),
      .i_ioaddr_brg(i_ioaddr_brg),
      .i_brg_bus(i_brg_bus),
      .en(b_en)
  );

recieve iDUT(
  .clk(clk),
  .b_en(b_en),
  .rst(rst),
  .i_iocs(i_iocs),
  .i_rx(i_rx),
  .i_iorw(i_iorw),
  .o_rda(o_rda),
  .o_data(o_data)
  );



  //try showing the reciver a value and then seeing if it acually "read" it in
  //correctly?
  task drive_val(input [7:0] val);
    integer i,j;
    //recall that a reciver transmission is done by
    //1) high to low
    //2) at every following b_en, a new value should be present (new bit?)
    //3) remain high

    //when called, set i_rx from high to low
    i_rx = 1'b0;
    for ( j = 0; j < 16; j = j + 1) @(posedge b_en);

    for ( i = 0; i < 8; i = i + 1) begin
      i_rx = val[i];
      //present some data
      //assumed that data is held for 16 b_en pulses?
      for ( j = 0; j < 16; j = j + 1) begin
        @(posedge b_en);
      end
    end

    i_rx=1'b1;
    for(j=0;j<16;j=j+1)@(posedge b_en);
  endtask

  //DETERMINE THE BAUD RATE TO TRY AND FEED INTO THE DUT FOR TESTING
  //buad rate of 9600, oversampling rate of n=4
  //i.e, generated b_en signal (ideally from baud rate module, but here just
  //generate it) 
  //baud rate of 9600 implies that 9600 bits are read per second. 
  //second. 
  //oversampling by n=4, or 2^n=16 implies that its actually 16 times faster(
  //improves resolution?). 
  //given that the clock here is set to be 10 ns period, 1*10^8 hz, 100 MHz
  //(100*10^6)?(16*9600)=651.04=651
  initial begin
    $dumpfile("recieve.vcd");
    $dumpvars(0, recieve_tb);
    i_ioaddr_brg = 2'b11;
    i_brg_bus = 8'h02;
    @(posedge clk);
    i_ioaddr_brg = 2'b10;
    i_brg_bus = 8'h8b;
    @(posedge clk);
    i_ioaddr_brg = 2'b00;
    i_brg_bus = 8'hff;

    drive_val(8'hab);
  end
endmodule

Minilab3/recieve.vcd
$date
	Tue Feb 17 09:03:21 2026
$end
$version
	ModelSim Version 2020.1
$end
$timescale
	1ps
$end

$scope module recieve_tb $end
$var reg 1 ! clk $end
$var reg 1 " b_en $end
$var reg 1 # rst $end
$var reg 1 $ i_iocs $end
$var reg 1 % i_rx $end
$var reg 1 & i_iorw $end
$var reg 1 ' o_rda $end
$var reg 8 ( o_data [7:0] $end
$var reg 2 ) i_ioaddr_brg [1:0] $end
$var reg 8 * i_brg_bus [7:0] $end

$scope task drive_val $end
$var reg 8 + val [7:0] $end
$var integer 32 , i $end
$var integer 32 - j $end
$upscope $end

$scope module baud_rate_gen $end
$var wire 1 . clk $end
$var wire 1 / rst $end
$var wire 1 0 i_ioaddr_brg [1] $end
$var wire 1 1 i_ioaddr_brg [0] $end
$var wire 1 2 i_brg_bus [7] $end
$var wire 1 3 i_brg_bus [6] $end
$var wire 1 4 i_brg_bus [5] $end
$var wire 1 5 i_brg_bus [4] $end
$var wire 1 6 i_brg_bus [3] $end
$var wire 1 7 i_brg_bus [2] $end
$var wire 1 8 i_brg_bus [1] $end
$var wire 1 9 i_brg_bus [0] $end
$var wire 1 : en $end
$var reg 16 ; div_buf [15:0] $end
$var reg 16 < down_counter [15:0] $end
$upscope $end

$scope module iDUT $end
$var parameter 2 = IDLE $end
$var parameter 2 > START_BIT $end
$var parameter 2 ? READING $end
$var parameter 2 @ END_BIT $end
$var wire 1 A clk $end
$var wire 1 B b_en $end
$var wire 1 C rst $end
$var wire 1 D i_iocs $end
$var wire 1 E i_rx $end
$var wire 1 F i_iorw $end
$var wire 1 G o_rda $end
$var wire 1 H o_data [7] $end
$var wire 1 I o_data [6] $end
$var wire 1 J o_data [5] $end
$var wire 1 K o_data [4] $end
$var wire 1 L o_data [3] $end
$var wire 1 M o_data [2] $end
$var wire 1 N o_data [1] $end
$var wire 1 O o_data [0] $end
$var reg 2 P curr_state [1:0] $end
$var reg 2 Q next_state [1:0] $end
$var reg 3 R counter [2:0] $end
$var reg 3 S start_counter [2:0] $end
$var reg 4 T t_counter [3:0] $end
$var reg 8 U buffer [7:0] $end
$var reg 1 V i_rx_reg $end
$var reg 1 W rda $end
$upscope $end
$upscope $end
$enddefinitions $end
#0
$dumpvars
0!
x"
1#
x$
1%
x&
x'
bx (
b11 )
b10 *
bx ;
bx <
bx P
b0 Q
bx R
bx S
bx T
bx U
xV
xW
bx +
b0 =
b1 >
b10 ?
b11 @
bx ,
bx -
0.
1/
11
10
09
18
07
06
05
04
03
02
x:
0A
xB
1C
xD
1E
xF
xG
xO
xN
xM
xL
xK
xJ
xI
xH
$end
#5
1!
1A
1.
b10 )
b10001011 *
19
16
12
01
b10xxxxxxxx ;
b10xxxxxxxx <
1V
0:
0"
0B
#10
0!
0A
0.
#15
1!
1A
1.
b0 )
b11111111 *
b10101011 +
0%
b0 -
17
15
14
13
00
0E
b1010001011 ;
b1010001011 <
#20
0!
0A
0.
#25
1!
1A
1.
b1010001010 <
0V
#30
0!
0A
0.
#35
1!
1A
1.
b1010001001 <
#40
0!
0A
0.
#45
1!
1A
1.
b1010001000 <
#50
0!
0A
0.
#55
1!
1A
1.
b1010000111 <
#60
0!
0A
0.
#65
1!
1A
1.
b1010000110 <
#70
0!
0A
0.
#75
1!
1A
1.
b1010000101 <
#80
0!
0A
0.
#85
1!
1A
1.
b1010000100 <
#90
0!
0A
0.
#95
1!
1A
1.
b1010000011 <
#100
0!
0A
0.
#105
1!
1A
1.
b1010000010 <
#110
0!
0A
0.
#115
1!
1A
1.
b1010000001 <
#120
0!
0A
0.
#125
1!
1A
1.
b1010000000 <
#130
0!
0A
0.
#135
1!
1A
1.
b1001111111 <
#140
0!
0A
0.
#145
1!
1A
1.
b1001111110 <
#150
0!
0A
0.
#155
1!
1A
1.
b1001111101 <
#160
0!
0A
0.
#165
1!
1A
1.
b1001111100 <
#170
0!
0A
0.
#175
1!
1A
1.
b1001111011 <
#180
0!
0A
0.
#185
1!
1A
1.
b1001111010 <
#190
0!
0A
0.
#195
1!
1A
1.
b1001111001 <
#200
0!
0A
0.
#205
1!
1A
1.
b1001111000 <
#210
0!
0A
0.
#215
1!
1A
1.
b1001110111 <
#220
0!
0A
0.
#225
1!
1A
1.
b1001110110 <
#230
0!
0A
0.
#235
1!
1A
1.
b1001110101 <
#240
0!
0A
0.
#245
1!
1A
1.
b1001110100 <
#250
0!
0A
0.
#255
1!
1A
1.
b1001110011 <
#260
0!
0A
0.
#265
1!
1A
1.
b1001110010 <
#270
0!
0A
0.
#275
1!
1A
1.
b1001110001 <
#280
0!
0A
0.
#285
1!
1A
1.
b1001110000 <
#290
0!
0A
0.
#295
1!
1A
1.
b1001101111 <
#300
0!
0A
0.
#305
1!
1A
1.
b1001101110 <
#310
0!
0A
0.
#315
1!
1A
1.
b1001101101 <
#320
0!
0A
0.
#325
1!
1A
1.
b1001101100 <
#330
0!
0A
0.
#335
1!
1A
1.
b1001101011 <
#340
0!
0A
0.
#345
1!
1A
1.
b1001101010 <
#350
0!
0A
0.
#355
1!
1A
1.
b1001101001 <
#360
0!
0A
0.
#365
1!
1A
1.
b1001101000 <
#370
0!
0A
0.
#375
1!
1A
1.
b1001100111 <
#380
0!
0A
0.
#385
1!
1A
1.
b1001100110 <
#390
0!
0A
0.
#395
1!
1A
1.
b1001100101 <
#400
0!
0A
0.
#405
1!
1A
1.
b1001100100 <
#410
0!
0A
0.
#415
1!
1A
1.
b1001100011 <
#420
0!
0A
0.
#425
1!
1A
1.
b1001100010 <
#430
0!
0A
0.
#435
1!
1A
1.
b1001100001 <
#440
0!
0A
0.
#445
1!
1A
1.
b1001100000 <
#450
0!
0A
0.
#455
1!
1A
1.
b1001011111 <
#460
0!
0A
0.
#465
1!
1A
1.
b1001011110 <
#470
0!
0A
0.
#475
1!
1A
1.
b1001011101 <
#480
0!
0A
0.
#485
1!
1A
1.
b1001011100 <
#490
0!
0A
0.
#495
1!
1A
1.
b1001011011 <
#500
0!
0A
0.
#505
1!
1A
1.
b1001011010 <
#510
0!
0A
0.
#515
1!
1A
1.
b1001011001 <
#520
0!
0A
0.
#525
1!
1A
1.
b1001011000 <
#530
0!
0A
0.
#535
1!
1A
1.
b1001010111 <
#540
0!
0A
0.
#545
1!
1A
1.
b1001010110 <
#550
0!
0A
0.
#555
1!
1A
1.
b1001010101 <
#560
0!
0A
0.
#565
1!
1A
1.
b1001010100 <
#570
0!
0A
0.
#575
1!
1A
1.
b1001010011 <
#580
0!
0A
0.
#585
1!
1A
1.
b1001010010 <
#590
0!
0A
0.
#595
1!
1A
1.
b1001010001 <
#600
0!
0A
0.
#605
1!
1A
1.
b1001010000 <
#610
0!
0A
0.
#615
1!
1A
1.
b1001001111 <
#620
0!
0A
0.
#625
1!
1A
1.
b1001001110 <
#630
0!
0A
0.
#635
1!
1A
1.
b1001001101 <
#640
0!
0A
0.
#645
1!
1A
1.
b1001001100 <
#650
0!
0A
0.
#655
1!
1A
1.
b1001001011 <
#660
0!
0A
0.
#665
1!
1A
1.
b1001001010 <
#670
0!
0A
0.
#675
1!
1A
1.
b1001001001 <
#680
0!
0A
0.
#685
1!
1A
1.
b1001001000 <
#690
0!
0A
0.
#695
1!
1A
1.
b1001000111 <
#700
0!
0A
0.
#705
1!
1A
1.
b1001000110 <
#710
0!
0A
0.
#715
1!
1A
1.
b1001000101 <
#720
0!
0A
0.
#725
1!
1A
1.
b1001000100 <
#730
0!
0A
0.
#735
1!
1A
1.
b1001000011 <
#740
0!
0A
0.
#745
1!
1A
1.
b1001000010 <
#750
0!
0A
0.
#755
1!
1A
1.
b1001000001 <
#760
0!
0A
0.
#765
1!
1A
1.
b1001000000 <
#770
0!
0A
0.
#775
1!
1A
1.
b1000111111 <
#780
0!
0A
0.
#785
1!
1A
1.
b1000111110 <
#790
0!
0A
0.
#795
1!
1A
1.
b1000111101 <
#800
0!
0A
0.
#805
1!
1A
1.
b1000111100 <
#810
0!
0A
0.
#815
1!
1A
1.
b1000111011 <
#820
0!
0A
0.
#825
1!
1A
1.
b1000111010 <
#830
0!
0A
0.
#835
1!
1A
1.
b1000111001 <
#840
0!
0A
0.
#845
1!
1A
1.
b1000111000 <
#850
0!
0A
0.
#855
1!
1A
1.
b1000110111 <
#860
0!
0A
0.
#865
1!
1A
1.
b1000110110 <
#870
0!
0A
0.
#875
1!
1A
1.
b1000110101 <
#880
0!
0A
0.
#885
1!
1A
1.
b1000110100 <
#890
0!
0A
0.
#895
1!
1A
1.
b1000110011 <
#900
0!
0A
0.
#905
1!
1A
1.
b1000110010 <
#910
0!
0A
0.
#915
1!
1A
1.
b1000110001 <
#920
0!
0A
0.
#925
1!
1A
1.
b1000110000 <
#930
0!
0A
0.
#935
1!
1A
1.
b1000101111 <
#940
0!
0A
0.
#945
1!
1A
1.
b1000101110 <
#950
0!
0A
0.
#955
1!
1A
1.
b1000101101 <
#960
0!
0A
0.
#965
1!
1A
1.
b1000101100 <
#970
0!
0A
0.
#975
1!
1A
1.
b1000101011 <
#980
0!
0A
0.
#985
1!
1A
1.
b1000101010 <
#990
0!
0A
0.
#995
1!
1A
1.
b1000101001 <
#1000
0!
0A
0.
#1005
1!
1A
1.
b1000101000 <
#1010
0!
0A
0.
#1015
1!
1A
1.
b1000100111 <
#1020
0!
0A
0.
#1025
1!
1A
1.
b1000100110 <
#1030
0!
0A
0.
#1035
1!
1A
1.
b1000100101 <
#1040
0!
0A
0.
#1045
1!
1A
1.
b1000100100 <
#1050
0!
0A
0.
#1055
1!
1A
1.
b1000100011 <
#1060
0!
0A
0.
#1065
1!
1A
1.
b1000100010 <
#1070
0!
0A
0.
#1075
1!
1A
1.
b1000100001 <
#1080
0!
0A
0.
#1085
1!
1A
1.
b1000100000 <
#1090
0!
0A
0.
#1095
1!
1A
1.
b1000011111 <
#1100
0!
0A
0.
#1105
1!
1A
1.
b1000011110 <
#1110
0!
0A
0.
#1115
1!
1A
1.
b1000011101 <
#1120
0!
0A
0.
#1125
1!
1A
1.
b1000011100 <
#1130
0!
0A
0.
#1135
1!
1A
1.
b1000011011 <
#1140
0!
0A
0.
#1145
1!
1A
1.
b1000011010 <
#1150
0!
0A
0.
#1155
1!
1A
1.
b1000011001 <
#1160
0!
0A
0.
#1165
1!
1A
1.
b1000011000 <
#1170
0!
0A
0.
#1175
1!
1A
1.
b1000010111 <
#1180
0!
0A
0.
#1185
1!
1A
1.
b1000010110 <
#1190
0!
0A
0.
#1195
1!
1A
1.
b1000010101 <
#1200
0!
0A
0.
#1205
1!
1A
1.
b1000010100 <
#1210
0!
0A
0.
#1215
1!
1A
1.
b1000010011 <
#1220
0!
0A
0.
#1225
1!
1A
1.
b1000010010 <
#1230
0!
0A
0.
#1235
1!
1A
1.
b1000010001 <
#1240
0!
0A
0.
#1245
1!
1A
1.
b1000010000 <
#1250
0!
0A
0.
#1255
1!
1A
1.
b1000001111 <
#1260
0!
0A
0.
#1265
1!
1A
1.
b1000001110 <
#1270
0!
0A
0.
#1275
1!
1A
1.
b1000001101 <
#1280
0!
0A
0.
#1285
1!
1A
1.
b1000001100 <
#1290
0!
0A
0.
#1295
1!
1A
1.
b1000001011 <
#1300
0!
0A
0.
#1305
1!
1A
1.
b1000001010 <
#1310
0!
0A
0.
#1315
1!
1A
1.
b1000001001 <
#1320
0!
0A
0.
#1325
1!
1A
1.
b1000001000 <
#1330
0!
0A
0.
#1335
1!
1A
1.
b1000000111 <
#1340
0!
0A
0.
#1345
1!
1A
1.
b1000000110 <
#1350
0!
0A
0.
#1355
1!
1A
1.
b1000000101 <
#1360
0!
0A
0.
#1365
1!
1A
1.
b1000000100 <
#1370
0!
0A
0.
#1375
1!
1A
1.
b1000000011 <
#1380
0!
0A
0.
#1385
1!
1A
1.
b1000000010 <
#1390
0!
0A
0.
#1395
1!
1A
1.
b1000000001 <
#1400
0!
0A
0.
#1405
1!
1A
1.
b1000000000 <
#1410
0!
0A
0.
#1415
1!
1A
1.
b111111111 <
#1420
0!
0A
0.
#1425
1!
1A
1.
b111111110 <
#1430
0!
0A
0.
#1435
1!
1A
1.
b111111101 <
#1440
0!
0A
0.
#1445
1!
1A
1.
b111111100 <
#1450
0!
0A
0.
#1455
1!
1A
1.
b111111011 <
#1460
0!
0A
0.
#1465
1!
1A
1.
b111111010 <
#1470
0!
0A
0.
#1475
1!
1A
1.
b111111001 <
#1480
0!
0A
0.
#1485
1!
1A
1.
b111111000 <
#1490
0!
0A
0.
#1495
1!
1A
1.
b111110111 <
#1500
0!
0A
0.
#1505
1!
1A
1.
b111110110 <
#1510
0!
0A
0.
#1515
1!
1A
1.
b111110101 <
#1520
0!
0A
0.
#1525
1!
1A
1.
b111110100 <
#1530
0!
0A
0.
#1535
1!
1A
1.
b111110011 <
#1540
0!
0A
0.
#1545
1!
1A
1.
b111110010 <
#1550
0!
0A
0.
#1555
1!
1A
1.
b111110001 <
#1560
0!
0A
0.
#1565
1!
1A
1.
b111110000 <
#1570
0!
0A
0.
#1575
1!
1A
1.
b111101111 <
#1580
0!
0A
0.
#1585
1!
1A
1.
b111101110 <
#1590
0!
0A
0.
#1595
1!
1A
1.
b111101101 <
#1600
0!
0A
0.
#1605
1!
1A
1.
b111101100 <
#1610
0!
0A
0.
#1615
1!
1A
1.
b111101011 <
#1620
0!
0A
0.
#1625
1!
1A
1.
b111101010 <
#1630
0!
0A
0.
#1635
1!
1A
1.
b111101001 <
#1640
0!
0A
0.
#1645
1!
1A
1.
b111101000 <
#1650
0!
0A
0.
#1655
1!
1A
1.
b111100111 <
#1660
0!
0A
0.
#1665
1!
1A
1.
b111100110 <
#1670
0!
0A
0.
#1675
1!
1A
1.
b111100101 <
#1680
0!
0A
0.
#1685
1!
1A
1.
b111100100 <
#1690
0!
0A
0.
#1695
1!
1A
1.
b111100011 <
#1700
0!
0A
0.
#1705
1!
1A
1.
b111100010 <
#1710
0!
0A
0.
#1715
1!
1A
1.
b111100001 <
#1720
0!
0A
0.
#1725
1!
1A
1.
b111100000 <
#1730
0!
0A
0.
#1735
1!
1A
1.
b111011111 <
#1740
0!
0A
0.
#1745
1!
1A
1.
b111011110 <
#1750
0!
0A
0.
#1755
1!
1A
1.
b111011101 <
#1760
0!
0A
0.
#1765
1!
1A
1.
b111011100 <
#1770
0!
0A
0.
#1775
1!
1A
1.
b111011011 <
#1780
0!
0A
0.
#1785
1!
1A
1.
b111011010 <
#1790
0!
0A
0.
#1795
1!
1A
1.
b111011001 <
#1800
0!
0A
0.
#1805
1!
1A
1.
b111011000 <
#1810
0!
0A
0.
#1815
1!
1A
1.
b111010111 <
#1820
0!
0A
0.
#1825
1!
1A
1.
b111010110 <
#1830
0!
0A
0.
#1835
1!
1A
1.
b111010101 <
#1840
0!
0A
0.
#1845
1!
1A
1.
b111010100 <
#1850
0!
0A
0.
#1855
1!
1A
1.
b111010011 <
#1860
0!
0A
0.
#1865
1!
1A
1.
b111010010 <
#1870
0!
0A
0.
#1875
1!
1A
1.
b111010001 <
#1880
0!
0A
0.
#1885
1!
1A
1.
b111010000 <
#1890
0!
0A
0.
#1895
1!
1A
1.
b111001111 <
#1900
0!
0A
0.
#1905
1!
1A
1.
b111001110 <
#1910
0!
0A
0.
#1915
1!
1A
1.
b111001101 <
#1920
0!
0A
0.
#1925
1!
1A
1.
b111001100 <
#1930
0!
0A
0.
#1935
1!
1A
1.
b111001011 <
#1940
0!
0A
0.
#1945
1!
1A
1.
b111001010 <
#1950
0!
0A
0.
#1955
1!
1A
1.
b111001001 <
#1960
0!
0A
0.
#1965
1!
1A
1.
b111001000 <
#1970
0!
0A
0.
#1975
1!
1A
1.
b111000111 <
#1980
0!
0A
0.
#1985
1!
1A
1.
b111000110 <
#1990
0!
0A
0.
#1995
1!
1A
1.
b111000101 <
#2000
0!
0A
0.
#2005
1!
1A
1.
b111000100 <
#2010
0!
0A
0.
#2015
1!
1A
1.
b111000011 <
#2020
0!
0A
0.
#2025
1!
1A
1.
b111000010 <
#2030
0!
0A
0.
#2035
1!
1A
1.
b111000001 <
#2040
0!
0A
0.
#2045
1!
1A
1.
b111000000 <
#2050
0!
0A
0.
#2055
1!
1A
1.
b110111111 <
#2060
0!
0A
0.
#2065
1!
1A
1.
b110111110 <
#2070
0!
0A
0.
#2075
1!
1A
1.
b110111101 <
#2080
0!
0A
0.
#2085
1!
1A
1.
b110111100 <
#2090
0!
0A
0.
#2095
1!
1A
1.
b110111011 <
#2100
0!
0A
0.
#2105
1!
1A
1.
b110111010 <
#2110
0!
0A
0.
#2115
1!
1A
1.
b110111001 <
#2120
0!
0A
0.
#2125
1!
1A
1.
b110111000 <
#2130
0!
0A
0.
#2135
1!
1A
1.
b110110111 <
#2140
0!
0A
0.
#2145
1!
1A
1.
b110110110 <
#2150
0!
0A
0.
#2155
1!
1A
1.
b110110101 <
#2160
0!
0A
0.
#2165
1!
1A
1.
b110110100 <
#2170
0!
0A
0.
#2175
1!
1A
1.
b110110011 <
#2180
0!
0A
0.
#2185
1!
1A
1.
b110110010 <
#2190
0!
0A
0.
#2195
1!
1A
1.
b110110001 <
#2200
0!
0A
0.
#2205
1!
1A
1.
b110110000 <
#2210
0!
0A
0.
#2215
1!
1A
1.
b110101111 <
#2220
0!
0A
0.
#2225
1!
1A
1.
b110101110 <
#2230
0!
0A
0.
#2235
1!
1A
1.
b110101101 <
#2240
0!
0A
0.
#2245
1!
1A
1.
b110101100 <
#2250
0!
0A
0.
#2255
1!
1A
1.
b110101011 <
#2260
0!
0A
0.
#2265
1!
1A
1.
b110101010 <
#2270
0!
0A
0.
#2275
1!
1A
1.
b110101001 <
#2280
0!
0A
0.
#2285
1!
1A
1.
b110101000 <
#2290
0!
0A
0.
#2295
1!
1A
1.
b110100111 <
#2300
0!
0A
0.
#2305
1!
1A
1.
b110100110 <
#2310
0!
0A
0.
#2315
1!
1A
1.
b110100101 <
#2320
0!
0A
0.
#2325
1!
1A
1.
b110100100 <
#2330
0!
0A
0.
#2335
1!
1A
1.
b110100011 <
#2340
0!
0A
0.
#2345
1!
1A
1.
b110100010 <
#2350
0!
0A
0.
#2355
1!
1A
1.
b110100001 <
#2360
0!
0A
0.
#2365
1!
1A
1.
b110100000 <
#2370
0!
0A
0.
#2375
1!
1A
1.
b110011111 <
#2380
0!
0A
0.
#2385
1!
1A
1.
b110011110 <
#2390
0!
0A
0.
#2395
1!
1A
1.
b110011101 <
#2400
0!
0A
0.
#2405
1!
1A
1.
b110011100 <
#2410
0!
0A
0.
#2415
1!
1A
1.
b110011011 <
#2420
0!
0A
0.
#2425
1!
1A
1.
b110011010 <
#2430
0!
0A
0.
#2435
1!
1A
1.
b110011001 <
#2440
0!
0A
0.
#2445
1!
1A
1.
b110011000 <
#2450
0!
0A
0.
#2455
1!
1A
1.
b110010111 <
#2460
0!
0A
0.
#2465
1!
1A
1.
b110010110 <
#2470
0!
0A
0.
#2475
1!
1A
1.
b110010101 <
#2480
0!
0A
0.
#2485
1!
1A
1.
b110010100 <
#2490
0!
0A
0.
#2495
1!
1A
1.
b110010011 <
#2500
0!
0A
0.
#2505
1!
1A
1.
b110010010 <
#2510
0!
0A
0.
#2515
1!
1A
1.
b110010001 <
#2520
0!
0A
0.
#2525
1!
1A
1.
b110010000 <
#2530
0!
0A
0.
#2535
1!
1A
1.
b110001111 <
#2540
0!
0A
0.
#2545
1!
1A
1.
b110001110 <
#2550
0!
0A
0.
#2555
1!
1A
1.
b110001101 <
#2560
0!
0A
0.
#2565
1!
1A
1.
b110001100 <
#2570
0!
0A
0.
#2575
1!
1A
1.
b110001011 <
#2580
0!
0A
0.
#2585
1!
1A
1.
b110001010 <
#2590
0!
0A
0.
#2595
1!
1A
1.
b110001001 <
#2600
0!
0A
0.
#2605
1!
1A
1.
b110001000 <
#2610
0!
0A
0.
#2615
1!
1A
1.
b110000111 <
#2620
0!
0A
0.
#2625
1!
1A
1.
b110000110 <
#2630
0!
0A
0.
#2635
1!
1A
1.
b110000101 <
#2640
0!
0A
0.
#2645
1!
1A
1.
b110000100 <
#2650
0!
0A
0.
#2655
1!
1A
1.
b110000011 <
#2660
0!
0A
0.
#2665
1!
1A
1.
b110000010 <
#2670
0!
0A
0.
#2675
1!
1A
1.
b110000001 <
#2680
0!
0A
0.
#2685
1!
1A
1.
b110000000 <
#2690
0!
0A
0.
#2695
1!
1A
1.
b101111111 <
#2700
0!
0A
0.
#2705
1!
1A
1.
b101111110 <
#2710
0!
0A
0.
#2715
1!
1A
1.
b101111101 <
#2720
0!
0A
0.
#2725
1!
1A
1.
b101111100 <
#2730
0!
0A
0.
#2735
1!
1A
1.
b101111011 <
#2740
0!
0A
0.
#2745
1!
1A
1.
b101111010 <
#2750
0!
0A
0.
#2755
1!
1A
1.
b101111001 <
#2760
0!
0A
0.
#2765
1!
1A
1.
b101111000 <
#2770
0!
0A
0.
#2775
1!
1A
1.
b101110111 <
#2780
0!
0A
0.
#2785
1!
1A
1.
b101110110 <
#2790
0!
0A
0.
#2795
1!
1A
1.
b101110101 <
#2800
0!
0A
0.
#2805
1!
1A
1.
b101110100 <
#2810
0!
0A
0.
#2815
1!
1A
1.
b101110011 <
#2820
0!
0A
0.
#2825
1!
1A
1.
b101110010 <
#2830
0!
0A
0.
#2835
1!
1A
1.
b101110001 <
#2840
0!
0A
0.
#2845
1!
1A
1.
b101110000 <
#2850
0!
0A
0.
#2855
1!
1A
1.
b101101111 <
#2860
0!
0A
0.
#2865
1!
1A
1.
b101101110 <
#2870
0!
0A
0.
#2875
1!
1A
1.
b101101101 <
#2880
0!
0A
0.
#2885
1!
1A
1.
b101101100 <
#2890
0!
0A
0.
#2895
1!
1A
1.
b101101011 <
#2900
0!
0A
0.
#2905
1!
1A
1.
b101101010 <
#2910
0!
0A
0.
#2915
1!
1A
1.
b101101001 <
#2920
0!
0A
0.
#2925
1!
1A
1.
b101101000 <
#2930
0!
0A
0.
#2935
1!
1A
1.
b101100111 <
#2940
0!
0A
0.
#2945
1!
1A
1.
b101100110 <
#2950
0!
0A
0.
#2955
1!
1A
1.
b101100101 <
#2960
0!
0A
0.
#2965
1!
1A
1.
b101100100 <
#2970
0!
0A
0.
#2975
1!
1A
1.
b101100011 <
#2980
0!
0A
0.
#2985
1!
1A
1.
b101100010 <
#2990
0!
0A
0.
#2995
1!
1A
1.
b101100001 <
#3000
0!
0A
0.
#3005
1!
1A
1.
b101100000 <
#3010
0!
0A
0.
#3015
1!
1A
1.
b101011111 <
#3020
0!
0A
0.
#3025
1!
1A
1.
b101011110 <
#3030
0!
0A
0.
#3035
1!
1A
1.
b101011101 <
#3040
0!
0A
0.
#3045
1!
1A
1.
b101011100 <
#3050
0!
0A
0.
#3055
1!
1A
1.
b101011011 <
#3060
0!
0A
0.
#3065
1!
1A
1.
b101011010 <
#3070
0!
0A
0.
#3075
1!
1A
1.
b101011001 <
#3080
0!
0A
0.
#3085
1!
1A
1.
b101011000 <
#3090
0!
0A
0.
#3095
1!
1A
1.
b101010111 <
#3100
0!
0A
0.
#3105
1!
1A
1.
b101010110 <
#3110
0!
0A
0.
#3115
1!
1A
1.
b101010101 <
#3120
0!
0A
0.
#3125
1!
1A
1.
b101010100 <
#3130
0!
0A
0.
#3135
1!
1A
1.
b101010011 <
#3140
0!
0A
0.
#3145
1!
1A
1.
b101010010 <
#3150
0!
0A
0.
#3155
1!
1A
1.
b101010001 <
#3160
0!
0A
0.
